{
    "input-las": "./ahn3/urban.las",
    "rural": "False",
    "urban": "True",
    "thinning-factor": 2,
    "gf-cellsize": 5,
    "gf-distance": 2,
    "gf-angle": 0.3,
    "idw": "True",
    "tin": "False",
    "idw-nn": 4,
    "idw-power": 2,
    "outU-las": "./ahn3/urban_classified.las",
    "outR-las": "./ahn3/rural_classified.las",
    "grid-cellsize": 2,
    "outU-grid-tin": "urbanOut-tin.asc",
    "outU-surf-tin": "urbanOut-tin.obj",
    "outU-grid-idw": "urbanOut-idw.asc",
    "outU-dsm": "urban_dsm.asc",
    "outR-grid-tin": "ruralOut-tin.asc",
    "outR-surf-tin": "ruralOut-tin.obj",
    "outR-grid-idw": "ruralOut-idw.asc",
    "outR-dsm": "rural_dsm.asc"
}